{
  "entityType" : "DEVICE",
  "entity" : {
    "additionalInfo" : {
      "gateway" : false,
      "overwriteActivityTime" : false,
      "description" : ""
    },
    "customerId" : {
      "entityType" : "CUSTOMER",
      "id" : "13814000-1dd2-11b2-8080-808080808080"
    },
    "deviceData" : {
      "configuration" : {
        "type" : "DEFAULT"
      },
      "transportConfiguration" : {
        "type" : "DEFAULT"
      }
    },
    "deviceProfileId" : {
      "entityType" : "DEVICE_PROFILE",
      "id" : "67af3860-8f1f-11f0-a61c-01e0c85fd5dd"
    },
    "externalId" : null,
    "firmwareId" : null,
    "id" : {
      "entityType" : "DEVICE",
      "id" : "50776240-cc95-11f0-b9be-a7eb49293647"
    },
    "label" : "",
    "name" : "simulador1",
    "softwareId" : null,
    "type" : "default"
  },
  "credentials" : {
    "credentialsId" : "3qSZXQfZeztRttey8iUm",
    "credentialsType" : "ACCESS_TOKEN",
    "credentialsValue" : null
  },
  "relations" : [ ],
  "attributes" : {
    "SERVER_SCOPE" : [ {
      "booleanValue" : false,
      "doubleValue" : null,
      "jsonValue" : null,
      "key" : "active",
      "lastUpdateTs" : 1764533642711,
      "longValue" : null,
      "strValue" : null
    }, {
      "booleanValue" : null,
      "doubleValue" : null,
      "jsonValue" : null,
      "key" : "c_unidades_ALAprimera",
      "lastUpdateTs" : 1764532937163,
      "longValue" : 2,
      "strValue" : null
    }, {
      "booleanValue" : null,
      "doubleValue" : null,
      "jsonValue" : null,
      "key" : "c_unidades_ensambladas",
      "lastUpdateTs" : 1764532985134,
      "longValue" : 3,
      "strValue" : null
    }, {
      "booleanValue" : null,
      "doubleValue" : null,
      "jsonValue" : null,
      "key" : "c_unidades_retrabajadas",
      "lastUpdateTs" : 1764532985134,
      "longValue" : 1,
      "strValue" : null
    }, {
      "booleanValue" : null,
      "doubleValue" : null,
      "jsonValue" : null,
      "key" : "caso",
      "lastUpdateTs" : 1764532937026,
      "longValue" : 3,
      "strValue" : null
    }, {
      "booleanValue" : null,
      "doubleValue" : null,
      "jsonValue" : null,
      "key" : "contador_levantamiento",
      "lastUpdateTs" : 1764532984999,
      "longValue" : 1,
      "strValue" : null
    }, {
      "booleanValue" : null,
      "doubleValue" : null,
      "jsonValue" : null,
      "key" : "evento",
      "lastUpdateTs" : 1764532123661,
      "longValue" : null,
      "strValue" : "FIN_ESTACION"
    }, {
      "booleanValue" : null,
      "doubleValue" : null,
      "jsonValue" : null,
      "key" : "filtrog",
      "lastUpdateTs" : 1764532123661,
      "longValue" : null,
      "strValue" : "no"
    }, {
      "booleanValue" : null,
      "doubleValue" : null,
      "jsonValue" : null,
      "key" : "id_mensaje",
      "lastUpdateTs" : 1764532984999,
      "longValue" : 3,
      "strValue" : null
    }, {
      "booleanValue" : null,
      "doubleValue" : null,
      "jsonValue" : null,
      "key" : "inactivityAlarmTime",
      "lastUpdateTs" : 1764533642708,
      "longValue" : 1764533642706,
      "strValue" : null
    }, {
      "booleanValue" : null,
      "doubleValue" : null,
      "jsonValue" : null,
      "key" : "lastActivityTime",
      "lastUpdateTs" : 1764532987638,
      "longValue" : 1764532985051,
      "strValue" : null
    }, {
      "booleanValue" : null,
      "doubleValue" : null,
      "jsonValue" : null,
      "key" : "lastConnectTime",
      "lastUpdateTs" : 1764532984872,
      "longValue" : 1764532984872,
      "strValue" : null
    }, {
      "booleanValue" : null,
      "doubleValue" : null,
      "jsonValue" : null,
      "key" : "lastDisconnectTime",
      "lastUpdateTs" : 1764532985073,
      "longValue" : 1764532985073,
      "strValue" : null
    }, {
      "booleanValue" : null,
      "doubleValue" : null,
      "jsonValue" : null,
      "key" : "names",
      "lastUpdateTs" : 1764532984999,
      "longValue" : 3,
      "strValue" : null
    }, {
      "booleanValue" : null,
      "doubleValue" : 0.67,
      "jsonValue" : null,
      "key" : "p_ALAprimera",
      "lastUpdateTs" : 1764532985134,
      "longValue" : null,
      "strValue" : null
    }, {
      "booleanValue" : null,
      "doubleValue" : 0.33,
      "jsonValue" : null,
      "key" : "p_retrabajadas",
      "lastUpdateTs" : 1764532985134,
      "longValue" : null,
      "strValue" : null
    }, {
      "booleanValue" : null,
      "doubleValue" : null,
      "jsonValue" : null,
      "key" : "ss_id_mensaje",
      "lastUpdateTs" : 1764532984999,
      "longValue" : 2,
      "strValue" : null
    }, {
      "booleanValue" : null,
      "doubleValue" : null,
      "jsonValue" : null,
      "key" : "unidad_terminada",
      "lastUpdateTs" : 1764532123661,
      "longValue" : null,
      "strValue" : "Y"
    }, {
      "booleanValue" : null,
      "doubleValue" : null,
      "jsonValue" : null,
      "key" : "unidades_ALAprimera",
      "lastUpdateTs" : 1764532835732,
      "longValue" : null,
      "strValue" : "true"
    }, {
      "booleanValue" : null,
      "doubleValue" : null,
      "jsonValue" : null,
      "key" : "unidades_ensambladas",
      "lastUpdateTs" : 1764532835732,
      "longValue" : 1,
      "strValue" : null
    }, {
      "booleanValue" : null,
      "doubleValue" : null,
      "jsonValue" : null,
      "key" : "unidades_retrabajadas",
      "lastUpdateTs" : 1764532985134,
      "longValue" : null,
      "strValue" : "true"
    } ],
    "SHARED_SCOPE" : [ ]
  },
  "calculatedFields" : [ ]
}