{
  "entityType" : "DEVICE",
  "entity" : {
    "additionalInfo" : {
      "gateway" : false,
      "overwriteActivityTime" : false,
      "description" : ""
    },
    "customerId" : {
      "entityType" : "CUSTOMER",
      "id" : "13814000-1dd2-11b2-8080-808080808080"
    },
    "deviceData" : {
      "configuration" : {
        "type" : "DEFAULT"
      },
      "transportConfiguration" : {
        "type" : "DEFAULT"
      }
    },
    "deviceProfileId" : {
      "entityType" : "DEVICE_PROFILE",
      "id" : "a26aa310-aed5-11f0-9abe-2dfd6db9cae3"
    },
    "externalId" : null,
    "firmwareId" : null,
    "id" : {
      "entityType" : "DEVICE",
      "id" : "a45fbc50-aed5-11f0-9abe-2dfd6db9cae3"
    },
    "label" : "",
    "name" : "Dummy Linea 1",
    "softwareId" : null,
    "type" : "dummy line"
  },
  "credentials" : {
    "credentialsId" : "ryfjU33IcfncnehAaMtL",
    "credentialsType" : "ACCESS_TOKEN",
    "credentialsValue" : null
  },
  "relations" : [ ],
  "attributes" : {
    "SERVER_SCOPE" : [ {
      "booleanValue" : false,
      "doubleValue" : null,
      "jsonValue" : null,
      "key" : "active",
      "lastUpdateTs" : 1761089939069,
      "longValue" : null,
      "strValue" : null
    }, {
      "booleanValue" : null,
      "doubleValue" : null,
      "jsonValue" : null,
      "key" : "inactivityAlarmTime",
      "lastUpdateTs" : 1761089939069,
      "longValue" : 1761089939068,
      "strValue" : null
    } ],
    "SHARED_SCOPE" : [ {
      "booleanValue" : null,
      "doubleValue" : null,
      "jsonValue" : null,
      "key" : "nombreDeLinea",
      "lastUpdateTs" : 1761089407559,
      "longValue" : null,
      "strValue" : "Linea 1"
    }, {
      "booleanValue" : null,
      "doubleValue" : null,
      "jsonValue" : null,
      "key" : "orden",
      "lastUpdateTs" : 1761090748634,
      "longValue" : 1,
      "strValue" : null
    } ]
  },
  "calculatedFields" : [ ]
}